marmiton/__init__.py
python_marmiton-0.2.1.dist-info/DESCRIPTION.rst
python_marmiton-0.2.1.dist-info/METADATA
python_marmiton-0.2.1.dist-info/RECORD
python_marmiton-0.2.1.dist-info/WHEEL
python_marmiton-0.2.1.dist-info/metadata.json
python_marmiton-0.2.1.dist-info/top_level.txt
