Metadata-Version: 2.0
Name: python-marmiton
Version: 0.2.1
Summary: Easy-to-use Python API for the marmiton.com cooking website.
Home-page: https://github.com/remaudcorentin-dev/python-marmiton
Author: Corentin Remaud
Author-email: remaudcorentin.dev@gmail.com
License: MIT
Platform: UNKNOWN
Requires-Dist: bs4
